odoo/addons/aresta/__init__.py
odoo/addons/aresta/__manifest__.py
odoo/addons/aresta/i18n/ca_ES.po
odoo/addons/aresta/i18n/es.po
odoo/addons/aresta/models/__init__.py
odoo/addons/aresta/models/sale_order.py
odoo/addons/aresta/report/__init__.py
odoo/addons/aresta/report/sale_report.py
odoo/addons/aresta/report/stock_report_deliveryslip.xml
odoo/addons/aresta/views/sale_order.xml
odoo/addons/aresta/views/sale_report.xml
odoo12_addon_aresta-12.0.0.0.4.dist-info/METADATA
odoo12_addon_aresta-12.0.0.0.4.dist-info/WHEEL
odoo12_addon_aresta-12.0.0.0.4.dist-info/top_level.txt
odoo12_addon_aresta-12.0.0.0.4.dist-info/RECORD
